{
  "name": "rokfor-writer",
  "author": "Rokfor & Urs Hofer",
  "homepage": "http://www.rokfor.ch/",
  "private": true,
  "version": "0.0.2",
  "main": "./www/index.js",
  "scripts": {
    "ionic:build": "ionic-app-scripts build",
    "ionic:serve": "ionic-app-scripts serve",
    "start": "electron ./www/index.js",
    "compile": "electron-packager . --platform mas --overwrite"
  },
  "dependencies": {
    "@angular/common": "2.4.8",
    "@angular/compiler": "2.4.8",
    "@angular/compiler-cli": "2.4.8",
    "@angular/core": "2.4.8",
    "@angular/forms": "2.4.8",
    "@angular/http": "2.4.8",
    "@angular/platform-browser": "2.4.8",
    "@angular/platform-browser-dynamic": "2.4.8",
    "@angular/platform-server": "2.4.8",
    "@ionic/storage": "2.0.0",
    "@types/pouchdb": "5.4.28",
    "app": "^0.1.0",
    "browser-window": "^0.4.0",
    "codemirror": "^5.25.0",
    "fs": "0.0.1-security",
    "ionic": "^2.2.1",
    "ionic-angular": "2.2.0",
    "ionic-native": "2.4.1",
    "ionicons": "3.0.0",
    "libstl": "^0.1.22",
    "mobx": "^2.7.0",
    "ng2-codemirror": "^1.1.1",
    "pouchdb": "^6.1.1",
    "rxjs": "5.0.1",
    "showdown": "^1.6.4",
    "sw-toolbox": "3.4.0",
    "zone.js": "0.7.2"
  },
  "devDependencies": {
    "@types/showdown": "^1.4.32",
    "electron": "^1.4.13",
    "@ionic/app-scripts": "1.1.4",
    "typescript": "2.0.9"
  },
  "cordovaPlugins": [
    "cordova-plugin-whitelist",
    "cordova-plugin-statusbar",
    "cordova-plugin-console",
    "cordova-plugin-device",
    "cordova-plugin-splashscreen",
    "ionic-plugin-keyboard"
  ],
  "cordovaPlatforms": [
    "ios",
    {
      "platform": "ios",
      "version": "",
      "locator": "ios"
    }
  ],
  "description": "Rokfor Writer: Editor for the Rokfor Writer Project."
}
